Workbook

Sheet Assumptions
A1: Economic Assessment — Group 3 geothermal binary plant
A2: Unit costs derived from Dr. Luca Xodo's lecture (Zero-Emission Binary example, slide 75-79); quantities scaled to Group 3's plant.
A4: PLANT / WELLFIELD DATA (Group 3)
A5: Production wells | B5: 5 | C5: n | D5: 5+5 doublet configuration (FEFLOW tutorial layout)
A6: Injection wells | B6: 5 | C6: n
A7: Total wells | B7: =B5+B6 -> 10 | C7: n
A8: Well pads | B8: 2 | C8: n | D8: 1 production pad + 1 injection pad (wells clustered by welldata X,Y)
A9: Well depth (bottom of screen) | B9: 1120 | C9: m | D9: geoth_tutorial_data_Group3.xlsx > welldata
A10: Net electrical power (Pel) | B10: 4223.9 | C10: kW | D10: from ORC_Group3.xlsx > Base_Case_Group3!B17
A11: Average Production Temperature (°C) | B11: 124.5327 | C11: °C | D11: Validated FEFLOW post-processing output (Stage 12), t = 100 yr; see ../outputs/Average_Production_Temperature.csv, ../figures/F8_average_production_temperature.png
A12: UNIT COSTS (from Xodo lecture, Zero-Emission Binary CAPEX table)
A13: Land acquisition | B13: 20000 | C13: €/ha
A14: EPC of well pad | B14: 700000 | C14: €/pad
A15: Design & management per well | B15: 400000 | C15: €/well
A16: Well drilling & testing (unit cost/m) | B16: 2200 | C16: €/m | D16: Scaled from Xodo reference example (2,500 m, >250 degC); linear depth-scaling assumption applied to Group 3 (1,120 m wells)
A17: Long production testing | B17: 500000 | C17: € (lump)
A18: EPC of power plant | B18: 2000000 | C18: €/MWg
A19: Substation & grid connection | B19: 500000 | C19: € (lump)
A20: Gathering system design & mgmt | B20: 750000 | C20: € (lump)
A21: Well pumps | B21: 400000 | C21: €/well (production wells)
A22: Piping & equipment | B22: 3000000 | C22: €/wellpad
A23: Permitting & surface exploration | B23: 2000000 | C23: € (lump)
A24: Land area assumed | B24: 10 | C24: ha | D24: same as Xodo example (2 wellpads)
A25: ORC plant auxiliaries (gross->net) | B25: 0.15 | C25: - | D25: assumption, matches Xodo binary example
A27: FINANCIAL PARAMETERS (Xodo Business Plan defaults)
A28: Discount rate (i) | B28: 0.1 | C28: -
A29: Plant useful life (n) | B29: 20 | C29: years
A30: Capacity factor (CF) | B30: 0.95 | C30: - | D30: 8,322 h/yr availability
A31: Availability | B31: =B30*8760 -> 8322 | C31: h/yr
A32: Variable O&M cost | B32: 13 | C32: €/MWh
A33: Fixed O&M cost | B33: 0 | C33: €/kW-yr | D33: assumption per lecture
A34: Capital Recovery Factor (CRF) | B34: =B28*(1+B28)^B29/((1+B28)^B29-1) -> 0.11745962 | C34: - | D34: CRF = i(1+i)^n / ((1+i)^n - 1)

Sheet CAPEX_Group3
A1: CAPEX Breakdown — Group 3 Geothermal Binary Plant
A2: Structure and unit costs from Xodo lecture (Zero-Emission Binary example); quantities from Assumptions sheet.
A4: Gross plant capacity (MWg) | B4: =Assumptions!B10/(1-Assumptions!B25)/1000 -> 4.9692941
A6: Task | B6: Unit | C6: Quantity | D6: Unit cost [€] | E6: Total cost [€] | F6: % of total
A7: Land acquisition and preparation | B7: ha | C7: =Assumptions!B24 -> 10 | D7: =Assumptions!B13 -> 20000 | E7: =C7*D7 -> 200000 | F7: =E7/$E$18 -> 0.003851443
A8: EPC of well pads | B8: n | C8: =Assumptions!B8 -> 2 | D8: =Assumptions!B14 -> 700000 | E8: =C8*D8 -> 1400000 | F8: =E8/$E$18 -> 0.026960101
A9: Design & management (all wells) | B9: n | C9: =Assumptions!B7 -> 10 | D9: =Assumptions!B15 -> 400000 | E9: =C9*D9 -> 4000000 | F9: =E9/$E$18 -> 0.077028861
A10: Well drilling & testing | B10: m (total) | C10: =Assumptions!B7*Assumptions!B9 -> 11200 | D10: =Assumptions!B16 -> 2200 | E10: =C10*D10 -> 24640000 | F10: =E10/$E$18 -> 0.47449778
A11: Long production testing | B11: lump | C11: 1 | D11: =Assumptions!B17 -> 500000 | E11: =C11*D11 -> 500000 | F11: =E11/$E$18 -> 0.0096286076
A12: EPC of the power plant | B12: MWg | C12: =B4 -> 4.9692941 | D12: =Assumptions!B18 -> 2000000 | E12: =C12*D12 -> 9938588.2 | F12: =E12/$E$18 -> 0.19138953
A13: Substation and grid connection | B13: lump | C13: 1 | D13: =Assumptions!B19 -> 500000 | E13: =C13*D13 -> 500000 | F13: =E13/$E$18 -> 0.0096286076
A14: Gathering: design & management | B14: lump | C14: 1 | D14: =Assumptions!B20 -> 750000 | E14: =C14*D14 -> 750000 | F14: =E14/$E$18 -> 0.014442911
A15: Gathering: well pumps | B15: n (prod. wells) | C15: =Assumptions!B5 -> 5 | D15: =Assumptions!B21 -> 400000 | E15: =C15*D15 -> 2000000 | F15: =E15/$E$18 -> 0.03851443
A16: Gathering: piping & equipment | B16: per wellpad | C16: =Assumptions!B8 -> 2 | D16: =Assumptions!B22 -> 3000000 | E16: =C16*D16 -> 6000000 | F16: =E16/$E$18 -> 0.11554329
A17: Permitting and surface exploration | B17: lump | C17: 1 | D17: =Assumptions!B23 -> 2000000 | E17: =C17*D17 -> 2000000 | F17: =E17/$E$18 -> 0.03851443
A18: TOTAL CAPEX | E18: =SUM(E7:E17) -> 51928588
A20: CAPEX per kW net installed | B20: =E18/Assumptions!B10 -> 12293.991

Sheet LCOE_Group3
A1: Simplified LCOE — Group 3
A2: sLCOE = (CAPEX/kW x CRF + Fixed O&M) / (8760 x CF) x 1000 + Variable O&M [Xodo lecture, based on NREL simplified LCOE]
A4: Total CAPEX | B4: =CAPEX_Group3!E18 -> 51928588
A5: Net electrical power | B5: =Assumptions!B10 -> 4223.9
A6: CAPEX per kW | B6: =B4/B5 -> 12293.991
A7: Capital Recovery Factor (CRF) | B7: =Assumptions!B34 -> 0.11745962
A8: Fixed O&M cost | B8: =Assumptions!B33 -> 0
A9: Availability | B9: =Assumptions!B31 -> 8322
A10: Variable O&M cost | B10: =Assumptions!B32 -> 13
A12: LCOE | B12: =(B6*B7+B8)/B9*1000+B10 -> 186.5217

Sheet Sensitivity
A1: Sensitivity Analysis — LCOE Spider Diagram (Group 3)
A2: Each parameter varied ±20%/±10% independently, all others held at base case. LMTair (condenser side) held fixed at base-case value (19.959 °C).
A4: Variation | B4: T_source-in [°C] | C4: LCOE (Tin) | D4: T_source-out [°C] | E4: LCOE (Tout) | F4: Flow rate [l/s] | G4: LCOE (Flow) | H4: Well depth [m] | I4: LCOE (Depth) | J4: Drilling cost [€/m] | K4: LCOE (DrillCost)
A5: -0.2 | B5: =Assumptions!$B$11*(1+A5) -> 99.62616 | C5: =(((17350000+((2200)*(1120)*10)+(2000000*(((((150)*0.917)*4.31*((B5)-(50)))*(0.52*(1-(273.15+19.9590607511086)/(273.15+(((B5)-(50))/LN((273.15+(B5))/(273.15+(50)))-273.15)))))/0.85/1000)))/((((150)*0.917)*4.31*((B5)-(50)))*(0.52*(1-(273.15+19.9590607511086)/(273.15+(((B5)-(50))/LN((273.15+(B5))/(273.15+(50)))-273.15))))))*0.117459624772546)/8322*1000+13 -> 294.20538 | D5: 40 | E5: =(((17350000+((2200)*(1120)*10)+(2000000*(((((150)*0.917)*4.31*((Assumptions!$B$11)-(40)))*(0.52*(1-(273.15+19.9590607511086)/(273.15+(((Assumptions!$B$11)-(40))/LN((273.15+(Assumptions!$B$11))/(273.15+(40)))-273.15)))))/0.85/1000)))/((((150)*0.917)*4.31*((Assumptions!$B$11)-(40)))*(0.52*(1-(273.15+19.9590607511086)/(273.15+(((Assumptions!$B$11)-(40))/LN((273.15+(Assumptions!$B$11))/(273.15+(40)))-273.15))))))*0.117459624772546)/8322*1000+13 -> 178.90785 | F5: 120 | G5: =(((17350000+((2200)*(1120)*10)+(2000000*(((((120)*0.917)*4.31*((Assumptions!$B$11)-(50)))*(0.52*(1-(273.15+19.9590607511086)/(273.15+(((Assumptions!$B$11)-(50))/LN((273.15+(Assumptions!$B$11))/(273.15+(50)))-273.15)))))/0.85/1000)))/((((120)*0.917)*4.31*((Assumptions!$B$11)-(50)))*(0.52*(1-(273.15+19.9590607511086)/(273.15+(((Assumptions!$B$11)-(50))/LN((273.15+(Assumptions!$B$11))/(273.15+(50)))-273.15))))))*0.117459624772546)/8322*1000+13 -> 221.60157 | H5: 896 | I5: =(((17350000+((2200)*(896)*10)+(2000000*(((((150)*0.917)*4.31*((Assumptions!$B$11)-(50)))*(0.52*(1-(273.15+19.9590607511086)/(273.15+(((Assumptions!$B$11)-(50))/LN((273.15+(Assumptions!$B$11))/(273.15+(50)))-273.15)))))/0.85/1000)))/((((150)*0.917)*4.31*((Assumptions!$B$11)-(50)))*(0.52*(1-(273.15+19.9590607511086)/(273.15+(((Assumptions!$B$11)-(50))/LN((273.15+(Assumptions!$B$11))/(273.15+(50)))-273.15))))))*0.117459624772546)/8322*1000+13 -> 170.05598 | J5: 1760 | K5: =(((17350000+((1760)*(1120)*10)+(2000000*(((((150)*0.917)*4.31*((Assumptions!$B$11)-(50)))*(0.52*(1-(273.15+19.9590607511086)/(273.15+(((Assumptions!$B$11)-(50))/LN((273.15+(Assumptions!$B$11))/(273.15+(50)))-273.15)))))/0.85/1000)))/((((150)*0.917)*4.31*((Assumptions!$B$11)-(50)))*(0.52*(1-(273.15+19.9590607511086)/(273.15+(((Assumptions!$B$11)-(50))/LN((273.15+(Assumptions!$B$11))/(273.15+(50)))-273.15))))))*0.117459624772546)/8322*1000+13 -> 170.05598
A6: -0.1 | B6: =Assumptions!$B$11*(1+A6) -> 112.07943 | C6: =(((17350000+((2200)*(1120)*10)+(2000000*(((((150)*0.917)*4.31*((B6)-(50)))*(0.52*(1-(273.15+19.9590607511086)/(273.15+(((B6)-(50))/LN((273.15+(B6))/(273.15+(50)))-273.15)))))/0.85/1000)))/((((150)*0.917)*4.31*((B6)-(50)))*(0.52*(1-(273.15+19.9590607511086)/(273.15+(((B6)-(50))/LN((273.15+(B6))/(273.15+(50)))-273.15))))))*0.117459624772546)/8322*1000+13 -> 228.03097 | D6: 45 | E6: =(((17350000+((2200)*(1120)*10)+(2000000*(((((150)*0.917)*4.31*((Assumptions!$B$11)-(45)))*(0.52*(1-(273.15+19.9590607511086)/(273.15+(((Assumptions!$B$11)-(45))/LN((273.15+(Assumptions!$B$11))/(273.15+(45)))-273.15)))))/0.85/1000)))/((((150)*0.917)*4.31*((Assumptions!$B$11)-(45)))*(0.52*(1-(273.15+19.9590607511086)/(273.15+(((Assumptions!$B$11)-(45))/LN((273.15+(Assumptions!$B$11))/(273.15+(45)))-273.15))))))*0.117459624772546)/8322*1000+13 -> 182.25993 | F6: 135 | G6: =(((17350000+((2200)*(1120)*10)+(2000000*(((((135)*0.917)*4.31*((Assumptions!$B$11)-(50)))*(0.52*(1-(273.15+19.9590607511086)/(273.15+(((Assumptions!$B$11)-(50))/LN((273.15+(Assumptions!$B$11))/(273.15+(50)))-273.15)))))/0.85/1000)))/((((135)*0.917)*4.31*((Assumptions!$B$11)-(50)))*(0.52*(1-(273.15+19.9590607511086)/(273.15+(((Assumptions!$B$11)-(50))/LN((273.15+(Assumptions!$B$11))/(273.15+(50)))-273.15))))))*0.117459624772546)/8322*1000+13 -> 202.11365 | H6: 1008 | I6: =(((17350000+((2200)*(1008)*10)+(2000000*(((((150)*0.917)*4.31*((Assumptions!$B$11)-(50)))*(0.52*(1-(273.15+19.9590607511086)/(273.15+(((Assumptions!$B$11)-(50))/LN((273.15+(Assumptions!$B$11))/(273.15+(50)))-273.15)))))/0.85/1000)))/((((150)*0.917)*4.31*((Assumptions!$B$11)-(50)))*(0.52*(1-(273.15+19.9590607511086)/(273.15+(((Assumptions!$B$11)-(50))/LN((273.15+(Assumptions!$B$11))/(273.15+(50)))-273.15))))))*0.117459624772546)/8322*1000+13 -> 178.28964 | J6: 1980 | K6: =(((17350000+((1980)*(1120)*10)+(2000000*(((((150)*0.917)*4.31*((Assumptions!$B$11)-(50)))*(0.52*(1-(273.15+19.9590607511086)/(273.15+(((Assumptions!$B$11)-(50))/LN((273.15+(Assumptions!$B$11))/(273.15+(50)))-273.15)))))/0.85/1000)))/((((150)*0.917)*4.31*((Assumptions!$B$11)-(50)))*(0.52*(1-(273.15+19.9590607511086)/(273.15+(((Assumptions!$B$11)-(50))/LN((273.15+(Assumptions!$B$11))/(273.15+(50)))-273.15))))))*0.117459624772546)/8322*1000+13 -> 178.28964
A7: 0 | B7: =Assumptions!$B$11 -> 124.5327 | C7: =LCOE_Group3!$B$12 -> 186.5217 | D7: 50 | E7: =LCOE_Group3!$B$12 -> 186.5217 | F7: 150 | G7: =LCOE_Group3!$B$12 -> 186.5217 | H7: 1120 | I7: =LCOE_Group3!$B$12 -> 186.5217 | J7: 2200 | K7: =LCOE_Group3!$B$12 -> 186.5217
A8: 0.1 | B8: =Assumptions!$B$11*(1+A8) -> 136.98597 | C8: =(((17350000+((2200)*(1120)*10)+(2000000*(((((150)*0.917)*4.31*((B8)-(50)))*(0.52*(1-(273.15+19.9590607511086)/(273.15+(((B8)-(50))/LN((273.15+(B8))/(273.15+(50)))-273.15)))))/0.85/1000)))/((((150)*0.917)*4.31*((B8)-(50)))*(0.52*(1-(273.15+19.9590607511086)/(273.15+(((B8)-(50))/LN((273.15+(B8))/(273.15+(50)))-273.15))))))*0.117459624772546)/8322*1000+13 -> 158.52567 | D8: 55 | E8: =(((17350000+((2200)*(1120)*10)+(2000000*(((((150)*0.917)*4.31*((Assumptions!$B$11)-(55)))*(0.52*(1-(273.15+19.9590607511086)/(273.15+(((Assumptions!$B$11)-(55))/LN((273.15+(Assumptions!$B$11))/(273.15+(55)))-273.15)))))/0.85/1000)))/((((150)*0.917)*4.31*((Assumptions!$B$11)-(55)))*(0.52*(1-(273.15+19.9590607511086)/(273.15+(((Assumptions!$B$11)-(55))/LN((273.15+(Assumptions!$B$11))/(273.15+(55)))-273.15))))))*0.117459624772546)/8322*1000+13 -> 191.83255 | F8: 165 | G8: =(((17350000+((2200)*(1120)*10)+(2000000*(((((165)*0.917)*4.31*((Assumptions!$B$11)-(50)))*(0.52*(1-(273.15+19.9590607511086)/(273.15+(((Assumptions!$B$11)-(50))/LN((273.15+(Assumptions!$B$11))/(273.15+(50)))-273.15)))))/0.85/1000)))/((((165)*0.917)*4.31*((Assumptions!$B$11)-(50)))*(0.52*(1-(273.15+19.9590607511086)/(273.15+(((Assumptions!$B$11)-(50))/LN((273.15+(Assumptions!$B$11))/(273.15+(50)))-273.15))))))*0.117459624772546)/8322*1000+13 -> 173.76757 | H8: 1232 | I8: =(((17350000+((2200)*(1232)*10)+(2000000*(((((150)*0.917)*4.31*((Assumptions!$B$11)-(50)))*(0.52*(1-(273.15+19.9590607511086)/(273.15+(((Assumptions!$B$11)-(50))/LN((273.15+(Assumptions!$B$11))/(273.15+(50)))-273.15)))))/0.85/1000)))/((((150)*0.917)*4.31*((Assumptions!$B$11)-(50)))*(0.52*(1-(273.15+19.9590607511086)/(273.15+(((Assumptions!$B$11)-(50))/LN((273.15+(Assumptions!$B$11))/(273.15+(50)))-273.15))))))*0.117459624772546)/8322*1000+13 -> 194.75696 | J8: 2420 | K8: =(((17350000+((2420)*(1120)*10)+(2000000*(((((150)*0.917)*4.31*((Assumptions!$B$11)-(50)))*(0.52*(1-(273.15+19.9590607511086)/(273.15+(((Assumptions!$B$11)-(50))/LN((273.15+(Assumptions!$B$11))/(273.15+(50)))-273.15)))))/0.85/1000)))/((((150)*0.917)*4.31*((Assumptions!$B$11)-(50)))*(0.52*(1-(273.15+19.9590607511086)/(273.15+(((Assumptions!$B$11)-(50))/LN((273.15+(Assumptions!$B$11))/(273.15+(50)))-273.15))))))*0.117459624772546)/8322*1000+13 -> 194.75696
A9: 0.2 | B9: =Assumptions!$B$11*(1+A9) -> 149.43924 | C9: =(((17350000+((2200)*(1120)*10)+(2000000*(((((150)*0.917)*4.31*((B9)-(50)))*(0.52*(1-(273.15+19.9590607511086)/(273.15+(((B9)-(50))/LN((273.15+(B9))/(273.15+(50)))-273.15)))))/0.85/1000)))/((((150)*0.917)*4.31*((B9)-(50)))*(0.52*(1-(273.15+19.9590607511086)/(273.15+(((B9)-(50))/LN((273.15+(B9))/(273.15+(50)))-273.15))))))*0.117459624772546)/8322*1000+13 -> 138.62569 | D9: 60 | E9: =(((17350000+((2200)*(1120)*10)+(2000000*(((((150)*0.917)*4.31*((Assumptions!$B$11)-(60)))*(0.52*(1-(273.15+19.9590607511086)/(273.15+(((Assumptions!$B$11)-(60))/LN((273.15+(Assumptions!$B$11))/(273.15+(60)))-273.15)))))/0.85/1000)))/((((150)*0.917)*4.31*((Assumptions!$B$11)-(60)))*(0.52*(1-(273.15+19.9590607511086)/(273.15+(((Assumptions!$B$11)-(60))/LN((273.15+(Assumptions!$B$11))/(273.15+(60)))-273.15))))))*0.117459624772546)/8322*1000+13 -> 198.37465 | F9: 180 | G9: =(((17350000+((2200)*(1120)*10)+(2000000*(((((180)*0.917)*4.31*((Assumptions!$B$11)-(50)))*(0.52*(1-(273.15+19.9590607511086)/(273.15+(((Assumptions!$B$11)-(50))/LN((273.15+(Assumptions!$B$11))/(273.15+(50)))-273.15)))))/0.85/1000)))/((((180)*0.917)*4.31*((Assumptions!$B$11)-(50)))*(0.52*(1-(273.15+19.9590607511086)/(273.15+(((Assumptions!$B$11)-(50))/LN((273.15+(Assumptions!$B$11))/(273.15+(50)))-273.15))))))*0.117459624772546)/8322*1000+13 -> 163.13779 | H9: 1344 | I9: =(((17350000+((2200)*(1344)*10)+(2000000*(((((150)*0.917)*4.31*((Assumptions!$B$11)-(50)))*(0.52*(1-(273.15+19.9590607511086)/(273.15+(((Assumptions!$B$11)-(50))/LN((273.15+(Assumptions!$B$11))/(273.15+(50)))-273.15)))))/0.85/1000)))/((((150)*0.917)*4.31*((Assumptions!$B$11)-(50)))*(0.52*(1-(273.15+19.9590607511086)/(273.15+(((Assumptions!$B$11)-(50))/LN((273.15+(Assumptions!$B$11))/(273.15+(50)))-273.15))))))*0.117459624772546)/8322*1000+13 -> 202.99063 | J9: 2640 | K9: =(((17350000+((2640)*(1120)*10)+(2000000*(((((150)*0.917)*4.31*((Assumptions!$B$11)-(50)))*(0.52*(1-(273.15+19.9590607511086)/(273.15+(((Assumptions!$B$11)-(50))/LN((273.15+(Assumptions!$B$11))/(273.15+(50)))-273.15)))))/0.85/1000)))/((((150)*0.917)*4.31*((Assumptions!$B$11)-(50)))*(0.52*(1-(273.15+19.9590607511086)/(273.15+(((Assumptions!$B$11)-(50))/LN((273.15+(Assumptions!$B$11))/(273.15+(50)))-273.15))))))*0.117459624772546)/8322*1000+13 -> 202.99063
